[
  {"français":"absolu","italiano":"assoluto","català":"absolut","português":"absoluto","română":"absolut","español":"absoluto","IV/english":"absolute"},
  {"français":"action","italiano":"azione","català":"accio","português":"accao","română":"actiune","español":"accion","IV/english":"action"},
  {"français":"acte","italiano":"atto","català":"acte","português":"a[c]to, auto","română":"act","español":"acto, auto","IV/english":"act"},
  {"français":"admirer","italiano":"ammirare","català":"admirar","português":"admirar","română":"a admira","español":"admirar","IV/english":"admire"},
  {"français":"admiration","italiano":"ammirazione","català":"admiracio","português":"admiracao","română":"admiratie","español":"admiracion","IV/english":"admiration"},
  {"français":"animal","italiano":"animale","català":"animal","português":"animal","română":"animal","español":"animal","IV/english":"animal"},
  {"français":"annoncer","italiano":"annunciare","català":"anunciar","português":"anunciar","română":"a anunta","español":"anunciar","IV/english":"announce"},
  {"français":"article","italiano":"articolo","català":"article","português":"artigo","română":"articol","español":"articulo","IV/english":"article"},
  {"français":"aspect","italiano":"aspetto","català":"aspecte","português":"aspecto","română":"aspect","español":"aspectio","IV/english":"aspect"},
  {"français":"attention","italiano":"attenzione","català":"atencio","português":"atencao","română":"atentie","español":"atencion","IV/english":"attention"},
  {"français":"auteur","italiano":"autore","català":"autor","português":"autor","română":"autor","español":"autor","IV/english":"author"},
  {"français":"autorite","italiano":"autorita","català":"autoritat","português":"autoridade","română":"autoritate","español":"autoridad","IV/english":"authority"},
  {"français":"cas","italiano":"caso","català":"cas","português":"caso","română":"caz","español":"caso","IV/english":"case"},
  {"français":"centre","italiano":"centro","català":"centre","português":"centro","română":"centru","español":"centro","IV/english":"centre"},
  {"français":"commerce","italiano":"commercio","català":"comerc","português":"comercio","română":"comert","español":"comercio","IV/english":"commerce"},
  {"français":"conscience","italiano":"conscienza","català":"consciencia","português":"consciencia","română":"constiina","español":"conciencia","IV/english":"conscience"},
  {"français":"continuer","italiano":"continuare","català":"continuar","português":"continuar","română":"a continua","español":"continuar","IV/english":"continue"},
  {"français":"curieux","italiano":"curioso","català":"curios","português":"curioso","română":"curios","español":"curioso","IV/english":"curious"},
  {"français":"declarer","italiano":"dichiarare","català":"declarar","português":"declarar","română":"a declara","español":"declarar","IV/english":"declare"},
  {"français":"delicat","italiano":"delicato","català":"delicat","português":"delicado","română":"delicat","español":"delicado","IV/english":"delicate"},
  {"français":"determiner","italiano":"determinare","català":"determinar","português":"determinar","română":"a determina","español":"determinar","IV/english":"determine"},
  {"français":"experience","italiano":"esperienza","català":"experiencia","português":"experiencia","română":"experienta","español":"experiencia","IV/english":"experience"},
  {"français":"expression","italiano":"espressione","català":"expressio","português":"expressao","română":"expresie","español":"expresion","IV/english":"expressive"},
  {"français":"figure","italiano":"figura","català":"figura","português":"figura","română":"figura","español":"figura","IV/english":"figure"},
  {"français":"fonction","italiano":"funzione","català":"funcio","português":"funcao","română":"functie","español":"funcion","IV/english":"function"},
  {"français":"genre","italiano":"genre","català":"genre","português":"genero","română":"gen","español":"genero","IV/english":"genre"},
  {"français":"grace","italiano":"grazia","català":"gracia","português":"graca","română":"gratie","español":"gracia","IV/english":"grace"},
  {"français":"histoire","italiano":"storia","català":"historia","português":"historia","română":"storie","español":"historia","IV/english":"history"},
  {"français":"horizon","italiano":"orizzonte","català":"horitzo","português":"horizonte","română":"orizont","español":"horizonte","IV/english":"horizon"},
  {"français":"illusion","italiano":"illusione","català":"il-lusio","português":"ilusao","română":"iluzie","español":"ilusion","IV/english":"illusion"},
  {"français":"image","italiano":"immagine","català":"imatge","português":"imagem","română":"imagine","español":"imagen","IV/english":"image"},
  {"français":"immense","italiano":"immenso","català":"immens","português":"imenso","română":"imens","español":"inmenso","IV/english":"immense"}
]
